{"type":"FeatureCollection","features":[{"type":"Feature","properties":{"marker-color":"#7773b5","marker-size":"medium","marker-symbol":"building","name":"1967 Gigot Ave","bed":5,"bath":2,"price":"$194,500"},"geometry":{"type":"Point","coordinates":[-98.31666111946106,49.9736712955787]}},{"type":"Feature","properties":{"marker-color":"#7773b5","marker-size":"medium","marker-symbol":"building","bed":3,"bath":2,"price":"$219,000"},"geometry":{"type":"Point","coordinates":[-98.28370213508606,49.96904453006377]}},{"type":"Feature","properties":{"marker-color":"#7773b5","marker-size":"medium","marker-symbol":"building","bed":3,"bath":2,"price":"$232,000"},"geometry":{"type":"Point","coordinates":[-98.3010560274124,49.988445674310036]}}]}
